pybamcmap/__init__.py
pybamcmap-0.3.1.dist-info/LICENSE
pybamcmap-0.3.1.dist-info/LICENSE.md
pybamcmap-0.3.1.dist-info/METADATA
pybamcmap-0.3.1.dist-info/WHEEL
pybamcmap-0.3.1.dist-info/top_level.txt
pybamcmap-0.3.1.dist-info/RECORD
