Metadata-Version: 2.1
Name: pybamcmap
Version: 0.3.1
Summary: A collection of colormaps using the CD of the Bundesanstalt für Materialforschung und -prüfung (BAM).
Home-page: https://github.com/dhufe/pybamcmap
Author: Daniel Hufschläger
Author-email: daniel@hufschlaeger.net
License: MIT
Platform: UNKNOWN
